{
	"info": {
		"_postman_id": "1e5b338b-4a45-49b9-8516-396876d85de0",
		"name": "CultureCare",
		"schema": "https://schema.getpostman.com/json/collection/v2.1.0/collection.json",
		"_exporter_id": "30345061",
		"_collection_link": "https://grey-spaceship-379791.postman.co/workspace/intro-to-backend~a029e6fd-d2e1-4456-859e-6538a912b507/collection/30345061-1e5b338b-4a45-49b9-8516-396876d85de0?action=share&source=collection_link&creator=30345061"
	},
	"item": [
		{
			"name": "create patient",
			"request": {
				"method": "POST",
				"header": [],
				"body": {
					"mode": "raw",
					"raw": "{\n    \"name\": \"Ambrose Blay\",\n    \"email_address\": \"ambrose2002blay@gmail.com\"\n}",
					"options": {
						"raw": {
							"language": "json"
						}
					}
				},
				"url": {
					"raw": "http://127.0.0.1:8000/patients/create/",
					"protocol": "http",
					"host": [
						"127",
						"0",
						"0",
						"1"
					],
					"port": "8000",
					"path": [
						"patients",
						"create",
						""
					]
				}
			},
			"response": []
		},
		{
			"name": "create practitioner",
			"request": {
				"method": "POST",
				"header": [],
				"body": {
					"mode": "raw",
					"raw": "{\n    \"name\": \"Dr. Blay\",\n    \"email_address\": \"einsteinblay@gmail.com\"\n}",
					"options": {
						"raw": {
							"language": "json"
						}
					}
				},
				"url": {
					"raw": "http://127.0.0.1:8000/practitioners/create/",
					"protocol": "http",
					"host": [
						"127",
						"0",
						"0",
						"1"
					],
					"port": "8000",
					"path": [
						"practitioners",
						"create",
						""
					]
				}
			},
			"response": []
		},
		{
			"name": "get practitioners",
			"request": {
				"method": "GET",
				"header": []
			},
			"response": []
		},
		{
			"name": "create email",
			"request": {
				"method": "GET",
				"header": []
			},
			"response": []
		},
		{
			"name": "send email",
			"request": {
				"method": "POST",
				"header": [],
				"body": {
					"mode": "raw",
					"raw": "{\n    \"practitioner_id\": 1,\n    \"patient_id\": 1\n}",
					"options": {
						"raw": {
							"language": "json"
						}
					}
				},
				"url": {
					"raw": "http://127.0.0.1:8000/emails/prewritten/send/1/",
					"protocol": "http",
					"host": [
						"127",
						"0",
						"0",
						"1"
					],
					"port": "8000",
					"path": [
						"emails",
						"prewritten",
						"send",
						"1",
						""
					]
				}
			},
			"response": []
		},
		{
			"name": "create form",
			"request": {
				"method": "GET",
				"header": []
			},
			"response": []
		}
	]
}